setup.py
LigParGen/BOSS2CHARMM.py
LigParGen/BOSS2GMX.py
LigParGen/BOSS2OPENMM.py
LigParGen/BOSS2Q.py
LigParGen/BOSS2XPLOR.py
LigParGen/BOSSReader.py
LigParGen/Converter.py
LigParGen/CreatZmat.py
LigParGen/Vector_algebra.py
LigParGen/__init__.py
LigParGen/fepzmat.py
LigParGen/mol_boss.py
LigParGen.egg-info/PKG-INFO
LigParGen.egg-info/SOURCES.txt
LigParGen.egg-info/dependency_links.txt
LigParGen.egg-info/entry_points.txt
LigParGen.egg-info/requires.txt
LigParGen.egg-info/top_level.txt