Metadata-Version: 1.1
Name: LigParGen
Version: 0.15
Summary: Python script to provide BOSS generated OPLS-AA/CM1A(-LBCC) parameters for organic molecules and ligands.
Home-page: https://bitbucket.org/leelasd/lpg_jan22_2018
Author: Leela S. Dodda, Matthew C. Robinson
Author-email: leela.dodda@yale.edu,matthew.robinson@yale.edu
License: MIT
Keywords: computational chemistry,force fields,molecular dynamics
Platform: UNKNOWN
Classifier: Programming Language :: Python :: 3.6
Classifier: Programming Language :: Python :: 2.7
Classifier: Topic :: Scientific/Engineering
